<?xml version="1.0" encoding="UTF.8" standalone="yes"?>

<menu>

<menu>
<title>[COLOR white]•[/COLOR] [B][COLOR purple]STREAMTAPE[/COLOR][/B]</title>
<thumbnail>https://i.imgur.com/xOWGNKN.png</thumbnail>
<fanart>https://i.imgur.com/RGwtxzj.jpg</fanart>
<urlsolve>https://streamtape.com/v/vxmRyBO7r6f4m7e/Juego_De_Tronos_720P_7X02.mp4</urlsolve>
</menu>

<menu>
<title>[COLOR white]•[/COLOR] [B][COLOR purple]VIDOZA[/COLOR][/B]</title>
<thumbnail>https://i.imgur.com/xOWGNKN.png</thumbnail>
<fanart>https://i.imgur.com/RGwtxzj.jpg</fanart>
<urlsolve>https://vidoza.net/eq056qj6xfzn.html</urlsolve>
</menu>

<menu>
<title>[COLOR white]•[/COLOR] [B][COLOR purple]DOODSTREAM[/COLOR][/B]</title>
<thumbnail>https://i.imgur.com/xOWGNKN.png</thumbnail>
<fanart>https://i.imgur.com/RGwtxzj.jpg</fanart>
<urlsolve>https://ds2play.com/d/c1l3jd9gyfhs</urlsolve>
</menu>

<menu>
<title>[COLOR white]•[/COLOR] [B][COLOR purple]GAMOVIDEO[/COLOR][/B]</title>
<thumbnail>https://i.imgur.com/xOWGNKN.png</thumbnail>
<fanart>https://i.imgur.com/RGwtxzj.jpg</fanart>
<urlsolve>https://gamovideo.com/91yxozrm8cd0</urlsolve>
</menu>

</menu>