<?xml version="1.0" encoding="UTF-8" standalone="yes"?>

<menus>
  
<menus_info>
<title>[COLOR red][/COLOR][COLOR yellow]MENUS[/COLOR][COLOR red][/COLOR]</title>
<genre>ALL</genre>
<description></description>
<thumbnail></thumbnail>
<fanart></fanart>
<credits></credits>
</menus_info>

<menu>
<title>[B][COLOR white]- SERIES[/COLOR][/B]</title>
<link>nolink</link>
<thumbnail>https://i.postimg.cc/sfqr7y78/bMJG1bN.png</thumbnail>
<fanart>https://i.postimg.cc/dDPpXs9V/UyNxG3U.jpg</fanart>
<externallink>https://raw.githubusercontent.com/fenix609/Addon_Fenix/main/Peliculas_Series/series/series_menu.xml</externallink>
</menu>

 
<menu>
<title>[B][COLOR white]- PELICULAS[/COLOR][/B]</title>
<link>nolink</link>
<thumbnail>https://i.postimg.cc/sfqr7y78/bMJG1bN.png</thumbnail>
<fanart>https://i.postimg.cc/dDPpXs9V/UyNxG3U.jpg</fanart>
<externallink>https://raw.githubusercontent.com/fenix609/Addon_Fenix/main/Peliculas_Series/peliculas/caballeros_zoodiaco/peliculas_menu.xml</externallink>
</menu>

</menus>